charidotella_extension_placeholder.cpython-311-x86_64-linux-musl.so
charidotella.libs/libstdc++-a9383cce.so.6.0.28
charidotella.libs/libgcc_s-a04fdf82.so.1
charidotella/utilities.py
charidotella/version.py
charidotella/animals.py
charidotella/__init__.py
charidotella/charidotella_extension_placeholder.c
charidotella/formats.py
charidotella/tasks/spectrogram.py
charidotella/tasks/spatiospectrogram.py
charidotella/tasks/__init__.py
charidotella/tasks/event_rate.py
charidotella/tasks/wiggle.py
charidotella/tasks/video.py
charidotella/tasks/colourtime.py
charidotella/assets/size
charidotella/assets/spectrogram
charidotella/assets/event_rate
charidotella/assets/es_to_frames
charidotella/assets/configuration-schema.json
charidotella/assets/spatiospectrogram
charidotella/filters/hot_pixels.py
charidotella/filters/transpose.py
charidotella/filters/__init__.py
charidotella/filters/default.py
charidotella/filters/refractory.py
charidotella/filters/arbiter_saturation.py
charidotella-3.1.0.dist-info/RECORD
charidotella-3.1.0.dist-info/WHEEL
charidotella-3.1.0.dist-info/METADATA
charidotella-3.1.0.dist-info/top_level.txt
charidotella-3.1.0.dist-info/entry_points.txt
