Metadata-Version: 2.1
Name: charidotella
Version: 3.1.0
Summary: Charidotella is a toolbox to organise and visualise Event Stream (.es) recordings
Home-page: https://github.com/neuromorphicsystems/charidotella
Author: Alexandre Marcireau
Author-email: alexandre.marcireau@gmail.com
Classifier: Programming Language :: Python :: 3
Classifier: License :: OSI Approved :: GNU General Public License v3 (GPLv3)
Classifier: Operating System :: OS Independent
Requires-Dist: aedat
Requires-Dist: colourtime
Requires-Dist: coolname
Requires-Dist: event-stream
Requires-Dist: jsonschema
Requires-Dist: matplotlib
Requires-Dist: pillow >=9.1
Requires-Dist: scipy
Requires-Dist: toml
